pta/__init__.py
pta/alphabet.py
pta/clock.py
pta/distributions.py
pta/pta.py
pta/spaces.py
pta/utils.py
pta/mdp/__init__.py
pta/mdp/digital_mdp.py
pta/mdp/mdp.py
pta/mdp/region_mdp.py
tests/__init__.py
tests/pta/__init__.py
tests/pta/test_clocks.py
tests/pta/test_region.py
probabilistic_timed_automata-0.1.2.dist-info/LICENSE
probabilistic_timed_automata-0.1.2.dist-info/METADATA
probabilistic_timed_automata-0.1.2.dist-info/WHEEL
probabilistic_timed_automata-0.1.2.dist-info/top_level.txt
probabilistic_timed_automata-0.1.2.dist-info/zip-safe
probabilistic_timed_automata-0.1.2.dist-info/RECORD
