Metadata-Version: 2.1
Name: probabilistic-timed-automata
Version: 0.1.2
Summary: Python library for building and simulating probabilistic timed automata.
Home-page: UNKNOWN
License: UNKNOWN
Platform: UNKNOWN
Classifier: Programming Language :: Python :: 3 :: Only
Classifier: Programming Language :: Python :: 3.6
Classifier: Programming Language :: Python :: 3.7
Classifier: Programming Language :: Python :: 3.8
Classifier: Intended Audience :: Science/Research
Requires-Python: ~=3.6
Requires-Dist: attrs (~=19.3.0)
Requires-Dist: portion (~=2.0.0)
Requires-Dist: typing-extensions
Provides-Extra: dev
Requires-Dist: autoflake (~=1.3.1) ; extra == 'dev'
Requires-Dist: black (~=19.10b0) ; extra == 'dev'
Requires-Dist: flake8 (~=3.7.9) ; extra == 'dev'
Requires-Dist: mypy (~=0.761) ; extra == 'dev'
Requires-Dist: codecov (~=2.0.22) ; extra == 'dev'
Requires-Dist: pytest (<5.4,>=5.0) ; extra == 'dev'
Requires-Dist: pytest-cov (~=2.8.1) ; extra == 'dev'
Requires-Dist: pytest-flake8 (~=1.0.4) ; extra == 'dev'
Requires-Dist: pytest-sugar (~=0.9.2) ; extra == 'dev'
Requires-Dist: pytest-xdist (~=1.31.0) ; extra == 'dev'
Requires-Dist: sphinx (~=3.0) ; extra == 'dev'
Requires-Dist: sphinx-better-theme (~=0.1.5) ; extra == 'dev'
Requires-Dist: recommonmark ; extra == 'dev'
